<StartList xmlns="http://www.orienteering.org/datastandard/3.0" xmlns:xsi="http://www.w3.org/2001/XMLSchema-instance" iofVersion="3.0" createTime="&lt;built-in method now of type object at 0x00007FFA5EA20F10&gt;" creator="SimulationSoftware"><Event>
    <Name>nxMpbF</Name>
    <StartTime>
        <Date>2020-01-08</Date>
        <Time>07:07:03</Time>
    </StartTime>
    <EndTime>
        <Date>2020-01-12</Date>
        <Time>18:01:06</Time>
    </EndTime>
</Event><ClassStart><Class>
    <Id>qZWPmr</Id>
    <Name>LAEBOK</Name>
</Class><Course>
    <Length>1762</Length>
    <Climb>241</Climb>
</Course><StartName>StartName0</StartName><PersonStart><EntryId>4176</EntryId><Person>
    <Id>FsCkAY</Id>
    <Name>
        <Family>Preston</Family>
        <Given>Alan</Given>
    </Name>
</Person><Organisation>
    <Id>zheaBS</Id>
    <Name>jyzYSg</Name>
    <Country code="GBR">JM</Country>
</Organisation><Start><BibNumber>10</BibNumber>
    <StartTime>2020-01-08</StartTime>
    <ControlCard>17544</ControlCard></Start></PersonStart><PersonStart><EntryId>6376</EntryId><Person>
    <Id>gbiCzc</Id>
    <Name>
        <Family>Lloyd</Family>
        <Given>Kathleen</Given>
    </Name>
</Person><Organisation>
    <Id>UFLSfW</Id>
    <Name>FpMTPY</Name>
    <Country code="GBR">DE</Country>
</Organisation><Start><BibNumber>10</BibNumber>
    <StartTime>2020-01-08</StartTime>
    <ControlCard>13101</ControlCard></Start></PersonStart><PersonStart><EntryId>5292</EntryId><Person>
    <Id>mwsPOR</Id>
    <Name>
        <Family>French</Family>
        <Given>Sarah</Given>
    </Name>
</Person><Organisation>
    <Id>VlpmZq</Id>
    <Name>vxasvA</Name>
    <Country code="GBR">EG</Country>
</Organisation><Start><BibNumber>10</BibNumber>
    <StartTime>2020-01-08</StartTime>
    <ControlCard>60186</ControlCard></Start></PersonStart><PersonStart><EntryId>7113</EntryId><Person>
    <Id>SfiDKE</Id>
    <Name>
        <Family>Longoria</Family>
        <Given>Renae</Given>
    </Name>
</Person><Organisation>
    <Id>uOyFtx</Id>
    <Name>mepfaA</Name>
    <Country code="GBR">BA</Country>
</Organisation><Start><BibNumber>0</BibNumber>
    <StartTime>2020-01-08</StartTime>
    <ControlCard>86590</ControlCard></Start></PersonStart><PersonStart><EntryId>8297</EntryId><Person>
    <Id>rudOpZ</Id>
    <Name>
        <Family>Yates</Family>
        <Given>Ian</Given>
    </Name>
</Person><Organisation>
    <Id>TywgLD</Id>
    <Name>GJCQeZ</Name>
    <Country code="GBR">BI</Country>
</Organisation><Start><BibNumber>8</BibNumber>
    <StartTime>2020-01-08</StartTime>
    <ControlCard>34886</ControlCard></Start></PersonStart></ClassStart><ClassStart><Class>
    <Id>aFqxGX</Id>
    <Name>wyWuNZ</Name>
</Class><Course>
    <Length>117</Length>
    <Climb>130</Climb>
</Course><StartName>StartName1</StartName><PersonStart><EntryId>4444</EntryId><Person>
    <Id>YFrvhY</Id>
    <Name>
        <Family>Shawl</Family>
        <Given>Jeanne</Given>
    </Name>
</Person><Organisation>
    <Id>tbvhUL</Id>
    <Name>NwdDuP</Name>
    <Country code="GBR">CI</Country>
</Organisation><Start><BibNumber>10</BibNumber>
    <StartTime>2020-01-08</StartTime>
    <ControlCard>22713</ControlCard></Start></PersonStart><PersonStart><EntryId>3273</EntryId><Person>
    <Id>wIFRWE</Id>
    <Name>
        <Family>Lucas</Family>
        <Given>Sharon</Given>
    </Name>
</Person><Organisation>
    <Id>ZYcRff</Id>
    <Name>neypCE</Name>
    <Country code="GBR">PF</Country>
</Organisation><Start><BibNumber>5</BibNumber>
    <StartTime>2020-01-08</StartTime>
    <ControlCard>50743</ControlCard></Start></PersonStart><PersonStart><EntryId>3857</EntryId><Person>
    <Id>pAfSWR</Id>
    <Name>
        <Family>Williams</Family>
        <Given>Chastity</Given>
    </Name>
</Person><Organisation>
    <Id>ofWnmT</Id>
    <Name>tlmSAk</Name>
    <Country code="GBR">BE</Country>
</Organisation><Start><BibNumber>7</BibNumber>
    <StartTime>2020-01-08</StartTime>
    <ControlCard>56132</ControlCard></Start></PersonStart><PersonStart><EntryId>2338</EntryId><Person>
    <Id>rrNcvO</Id>
    <Name>
        <Family>Forrest</Family>
        <Given>Ross</Given>
    </Name>
</Person><Organisation>
    <Id>tgyPvs</Id>
    <Name>mlAfiJ</Name>
    <Country code="GBR">GD</Country>
</Organisation><Start><BibNumber>8</BibNumber>
    <StartTime>2020-01-08</StartTime>
    <ControlCard>40666</ControlCard></Start></PersonStart><PersonStart><EntryId>6616</EntryId><Person>
    <Id>BHJuvR</Id>
    <Name>
        <Family>Thane</Family>
        <Given>Rashad</Given>
    </Name>
</Person><Organisation>
    <Id>xuIVrV</Id>
    <Name>lnzMCI</Name>
    <Country code="GBR">ZM</Country>
</Organisation><Start><BibNumber>1</BibNumber>
    <StartTime>2020-01-08</StartTime>
    <ControlCard>14200</ControlCard></Start></PersonStart></ClassStart><ClassStart><Class>
    <Id>NFAYla</Id>
    <Name>DuZkHz</Name>
</Class><Course>
    <Length>502</Length>
    <Climb>838</Climb>
</Course><StartName>StartName2</StartName><PersonStart><EntryId>3313</EntryId><Person>
    <Id>xpYANd</Id>
    <Name>
        <Family>Fugate</Family>
        <Given>Angelina</Given>
    </Name>
</Person><Organisation>
    <Id>GGYkkP</Id>
    <Name>TUChIu</Name>
    <Country code="GBR">NU</Country>
</Organisation><Start><BibNumber>0</BibNumber>
    <StartTime>2020-01-08</StartTime>
    <ControlCard>81446</ControlCard></Start></PersonStart><PersonStart><EntryId>7952</EntryId><Person>
    <Id>mlwzPr</Id>
    <Name>
        <Family>Traverso</Family>
        <Given>Kari</Given>
    </Name>
</Person><Organisation>
    <Id>JeUXlN</Id>
    <Name>PrpxeE</Name>
    <Country code="GBR">AN</Country>
</Organisation><Start><BibNumber>4</BibNumber>
    <StartTime>2020-01-08</StartTime>
    <ControlCard>93299</ControlCard></Start></PersonStart><PersonStart><EntryId>1895</EntryId><Person>
    <Id>Fllhdx</Id>
    <Name>
        <Family>Greene</Family>
        <Given>Theresa</Given>
    </Name>
</Person><Organisation>
    <Id>HZOlaB</Id>
    <Name>lAZiEd</Name>
    <Country code="GBR">KE</Country>
</Organisation><Start><BibNumber>3</BibNumber>
    <StartTime>2020-01-08</StartTime>
    <ControlCard>14956</ControlCard></Start></PersonStart></ClassStart><ClassStart><Class>
    <Id>OcXtxF</Id>
    <Name>rDNItv</Name>
</Class><Course>
    <Length>212</Length>
    <Climb>678</Climb>
</Course><StartName>StartName3</StartName><PersonStart><EntryId>2169</EntryId><Person>
    <Id>DevLBH</Id>
    <Name>
        <Family>Hecker</Family>
        <Given>Dessie</Given>
    </Name>
</Person><Organisation>
    <Id>PNZkyS</Id>
    <Name>YyORpm</Name>
    <Country code="GBR">SM</Country>
</Organisation><Start><BibNumber>10</BibNumber>
    <StartTime>2020-01-08</StartTime>
    <ControlCard>75078</ControlCard></Start></PersonStart><PersonStart><EntryId>4378</EntryId><Person>
    <Id>BLhIbT</Id>
    <Name>
        <Family>Cunningham</Family>
        <Given>Danielle</Given>
    </Name>
</Person><Organisation>
    <Id>WnCOWV</Id>
    <Name>btfPBi</Name>
    <Country code="GBR">TN</Country>
</Organisation><Start><BibNumber>6</BibNumber>
    <StartTime>2020-01-08</StartTime>
    <ControlCard>92801</ControlCard></Start></PersonStart><PersonStart><EntryId>8573</EntryId><Person>
    <Id>lQBnOS</Id>
    <Name>
        <Family>Nelson</Family>
        <Given>Joseph</Given>
    </Name>
</Person><Organisation>
    <Id>ZZOSJl</Id>
    <Name>qINaTC</Name>
    <Country code="GBR">VN</Country>
</Organisation><Start><BibNumber>6</BibNumber>
    <StartTime>2020-01-08</StartTime>
    <ControlCard>79606</ControlCard></Start></PersonStart><PersonStart><EntryId>4909</EntryId><Person>
    <Id>nUgChY</Id>
    <Name>
        <Family>Sollie</Family>
        <Given>Jeff</Given>
    </Name>
</Person><Organisation>
    <Id>ycywER</Id>
    <Name>sdnHyb</Name>
    <Country code="GBR">BB</Country>
</Organisation><Start><BibNumber>5</BibNumber>
    <StartTime>2020-01-08</StartTime>
    <ControlCard>97256</ControlCard></Start></PersonStart></ClassStart><ClassStart><Class>
    <Id>hrcSvd</Id>
    <Name>ROSYdo</Name>
</Class><Course>
    <Length>956</Length>
    <Climb>884</Climb>
</Course><StartName>StartName4</StartName><PersonStart><EntryId>4615</EntryId><Person>
    <Id>neszqM</Id>
    <Name>
        <Family>Greer</Family>
        <Given>Daniele</Given>
    </Name>
</Person><Organisation>
    <Id>WMMVVv</Id>
    <Name>FfDFuy</Name>
    <Country code="GBR">MM</Country>
</Organisation><Start><BibNumber>8</BibNumber>
    <StartTime>2020-01-08</StartTime>
    <ControlCard>24044</ControlCard></Start></PersonStart><PersonStart><EntryId>5433</EntryId><Person>
    <Id>WUYMZM</Id>
    <Name>
        <Family>Bennett</Family>
        <Given>Donald</Given>
    </Name>
</Person><Organisation>
    <Id>nfmsVW</Id>
    <Name>QupxGr</Name>
    <Country code="GBR">LS</Country>
</Organisation><Start><BibNumber>8</BibNumber>
    <StartTime>2020-01-08</StartTime>
    <ControlCard>56098</ControlCard></Start></PersonStart><PersonStart><EntryId>9740</EntryId><Person>
    <Id>XWcMsR</Id>
    <Name>
        <Family>Gonzalez</Family>
        <Given>Marlene</Given>
    </Name>
</Person><Organisation>
    <Id>EUdzGv</Id>
    <Name>vmBMkP</Name>
    <Country code="GBR">SK</Country>
</Organisation><Start><BibNumber>5</BibNumber>
    <StartTime>2020-01-08</StartTime>
    <ControlCard>84141</ControlCard></Start></PersonStart><PersonStart><EntryId>5417</EntryId><Person>
    <Id>NJkgdA</Id>
    <Name>
        <Family>Casarez</Family>
        <Given>Christine</Given>
    </Name>
</Person><Organisation>
    <Id>yZxJxi</Id>
    <Name>KRTlfD</Name>
    <Country code="GBR">LC</Country>
</Organisation><Start><BibNumber>1</BibNumber>
    <StartTime>2020-01-08</StartTime>
    <ControlCard>80352</ControlCard></Start></PersonStart><PersonStart><EntryId>7817</EntryId><Person>
    <Id>RjFdag</Id>
    <Name>
        <Family>Odom</Family>
        <Given>Janet</Given>
    </Name>
</Person><Organisation>
    <Id>RnHVqv</Id>
    <Name>ASWwYK</Name>
    <Country code="GBR">CY</Country>
</Organisation><Start><BibNumber>6</BibNumber>
    <StartTime>2020-01-08</StartTime>
    <ControlCard>15664</ControlCard></Start></PersonStart></ClassStart></StartList>